src/_4_LUT_Baungarten.v
module _4_LUT_Baungarten(
input [3:0] i_addr_load_data,
input i_Data,
input [3:0] i_LUT,
input i_config_enable,
output reg o_Data
);

reg [15:0] r_data;
always@*
begin
	if(i_config_enable)
	begin
		case(i_addr_load_data)
		4'd0:r_data[0] = i_Data;
		4'd1:r_data[1] = i_Data;
		4'd2:r_data[2] = i_Data;
		4'd3:r_data[3] = i_Data;
		4'd4:r_data[4] = i_Data;
		4'd5:r_data[5] = i_Data;
		4'd6:r_data[6] = i_Data;
		4'd7:r_data[7] = i_Data;
		4'd8:r_data[8] = i_Data;
		4'd9:r_data[9] = i_Data;
		4'd10:r_data[10] = i_Data;
		4'd11:r_data[11] = i_Data;
		4'd12:r_data[12] = i_Data;
		4'd13:r_data[13] = i_Data;
		4'd14:r_data[14] = i_Data;
		4'd15:r_data[15] = i_Data;
		endcase
	end
	else
	begin
		case(i_LUT)
		4'd0:o_Data=r_data[0];
		4'd1:o_Data=r_data[1];
		4'd2:o_Data=r_data[2];
		4'd3:o_Data=r_data[3];
		4'd4:o_Data=r_data[4];
		4'd5:o_Data=r_data[5];
		4'd6:o_Data=r_data[6];
		4'd7:o_Data=r_data[7];
		4'd8:o_Data=r_data[8];
		4'd9:o_Data=r_data[9];
		4'd10:o_Data=r_data[10];
		4'd11:o_Data=r_data[11];
		4'd12:o_Data=r_data[12];
		4'd13:o_Data=r_data[13];
		4'd14:o_Data=r_data[14];
		4'd15:o_Data=r_data[15];
		endcase
	end
end



endmodule

src/TB_4_LUT_Baungarten.v
module TB_4_LUT_Baungarten();

reg [3:0] i_addr_load_data;
reg i_Data;
reg [3:0] i_LUT;
reg i_config_enable;
wire o_Data;

_4_LUT_Baungarten DUT(
.i_addr_load_data (i_addr_load_data),
.i_Data (i_Data),
.i_LUT (i_LUT),
.i_config_enable (i_config_enable),
.o_Data (o_Data)
);

initial
begin
i_addr_load_data = 0;
i_Data = 0;
i_LUT = 0;
i_config_enable = 1;
#50;
i_Data=1;
#50;
i_addr_load_data = i_addr_load_data + 1; // 1
#50;
i_addr_load_data = i_addr_load_data + 1; //2 
#50;
i_addr_load_data = i_addr_load_data + 1;//3
#50;
i_addr_load_data = i_addr_load_data + 1;//4
#50;
i_addr_load_data = i_addr_load_data + 1;//5
#50;
i_addr_load_data = i_addr_load_data + 1;//6
#50;
i_addr_load_data = i_addr_load_data + 1;//7
#50;
i_addr_load_data = i_addr_load_data + 1;//8
#50;
i_addr_load_data = i_addr_load_data + 1;//9
i_Data=0;
#50;
i_addr_load_data = i_addr_load_data + 1;//10
#50;
i_addr_load_data = i_addr_load_data + 1;//11
#50;
i_addr_load_data = i_addr_load_data + 1;//12
#50;
i_addr_load_data = i_addr_load_data + 1;//13
#50;
i_addr_load_data = i_addr_load_data + 1;//14
#50;
i_addr_load_data = i_addr_load_data + 1;//15
#100;
i_config_enable = 0;
#50;
i_LUT = i_LUT + 1; //1
#50;
i_LUT = i_LUT + 1;
#50;
i_LUT = i_LUT + 1;
#50;
i_LUT = i_LUT + 1;
#50;
i_LUT = i_LUT + 1;
#50;
i_LUT = i_LUT + 1;
#50;
i_LUT = i_LUT + 1;
#50;
i_LUT = i_LUT + 1;
#50;
i_LUT = i_LUT + 1;
#50;
i_LUT = i_LUT + 1;
#50;
i_LUT = i_LUT + 1;
#50;
i_LUT = i_LUT + 1;
#50;
i_LUT = i_LUT + 1;
#50;
i_LUT = i_LUT + 1;
#50;
i_LUT = i_LUT + 1;
#50;
i_LUT = i_LUT + 1;
#100
i_LUT = 0;
#50;
end

  initial
  begin
  $dumpfile("TB_4_LUT_Baungarten.vcd");
  $dumpvars;
  end
endmodule

src/TB_4_LUT_Baungarten.vcd
$date
	Mon Aug 28 16:12:30 2023
$end
$version
	Icarus Verilog
$end
$timescale
	1s
$end
$scope module TB_4_LUT_Baungarten $end
$var wire 1 ! o_Data $end
$var reg 1 " i_Data $end
$var reg 4 # i_LUT [3:0] $end
$var reg 4 $ i_addr_load_data [3:0] $end
$var reg 1 % i_config_enable $end
$scope module DUT $end
$var wire 1 " i_Data $end
$var wire 4 & i_LUT [3:0] $end
$var wire 4 ' i_addr_load_data [3:0] $end
$var wire 1 % i_config_enable $end
$var reg 1 ! o_Data $end
$var reg 16 ( r_data [15:0] $end
$upscope $end
$upscope $end
$enddefinitions $end
#0
$dumpvars
bx0 (
b0 '
b0 &
1%
b0 $
b0 #
0"
x!
$end
#50
bx1 (
1"
#100
bx11 (
b1 $
b1 '
#150
bx111 (
b10 $
b10 '
#200
bx1111 (
b11 $
b11 '
#250
bx11111 (
b100 $
b100 '
#300
bx111111 (
b101 $
b101 '
#350
bx1111111 (
b110 $
b110 '
#400
bx11111111 (
b111 $
b111 '
#450
bx111111111 (
b1000 $
b1000 '
#500
bx0111111111 (
0"
b1001 $
b1001 '
#550
bx00111111111 (
b1010 $
b1010 '
#600
bx000111111111 (
b1011 $
b1011 '
#650
bx0000111111111 (
b1100 $
b1100 '
#700
bx00000111111111 (
b1101 $
b1101 '
#750
bx000000111111111 (
b1110 $
b1110 '
#800
b111111111 (
b1111 $
b1111 '
#900
1!
0%
#950
b1 #
b1 &
#1000
b10 #
b10 &
#1050
b11 #
b11 &
#1100
b100 #
b100 &
#1150
b101 #
b101 &
#1200
b110 #
b110 &
#1250
b111 #
b111 &
#1300
b1000 #
b1000 &
#1350
0!
b1001 #
b1001 &
#1400
b1010 #
b1010 &
#1450
b1011 #
b1011 &
#1500
b1100 #
b1100 &
#1550
b1101 #
b1101 &
#1600
b1110 #
b1110 &
#1650
b1111 #
b1111 &
#1700
1!
b0 #
b0 &
