src/Single_4LUT.v


module Single_4LUT(
input [3:0] i_addr_load_data,
input i_Data,
input [3:0] i_LUT,
input i_config_enable,
output reg o_Data
);
	
	
reg [15:0] r_data;
always@*
begin
	if(i_config_enable)
	begin
		case(i_addr_load_data)
		4'd0:r_data[0] = i_Data;
		4'd1:r_data[1] = i_Data;
		4'd2:r_data[2] = i_Data;
		4'd3:r_data[3] = i_Data;
		4'd4:r_data[4] = i_Data;
		4'd5:r_data[5] = i_Data;
		4'd6:r_data[6] = i_Data;
		4'd7:r_data[7] = i_Data;
		4'd8:r_data[8] = i_Data;
		4'd9:r_data[9] = i_Data;
		4'd10:r_data[10] = i_Data;
		4'd11:r_data[11] = i_Data;
		4'd12:r_data[12] = i_Data;
		4'd13:r_data[13] = i_Data;
		4'd14:r_data[14] = i_Data;
		4'd15:r_data[15] = i_Data;
		endcase
	end
	else
	begin
		case(i_LUT)
		4'd0:o_Data=r_data[0];
		4'd1:o_Data=r_data[1];
		4'd2:o_Data=r_data[2];
		4'd3:o_Data=r_data[3];
		4'd4:o_Data=r_data[4];
		4'd5:o_Data=r_data[5];
		4'd6:o_Data=r_data[6];
		4'd7:o_Data=r_data[7];
		4'd8:o_Data=r_data[8];
		4'd9:o_Data=r_data[9];
		4'd10:o_Data=r_data[10];
		4'd11:o_Data=r_data[11];
		4'd12:o_Data=r_data[12];
		4'd13:o_Data=r_data[13];
		4'd14:o_Data=r_data[14];
		4'd15:o_Data=r_data[15];
		endcase
	end
end





endmodule

src/tt_um_4_LUT_Baungarten.v


module tt_um_4_LUT_Baungarten(
    input  wire [7:0] ui_in,    // Dedicated inputs - connected to the input switches
    output wire [7:0] uo_out,   // Dedicated outputs - connected to the 7 segment display
    input  wire [7:0] uio_in,   // IOs: Bidirectional Input path
    output wire [7:0] uio_out,  // IOs: Bidirectional Output path
    output wire [7:0] uio_oe,   // IOs: Bidirectional Enable path (active high: 0=input, 1=output)
    input  wire       ena,      // will go high when the design is enabled
    input  wire       clk,      // clock
    input  wire       rst_n     // reset_n - low to reset
);

wire [1:0] Lut_mux;

//LUT1	
reg [3:0] i_addr_load_data_L1;
reg i_Data_L1;
wire [3:0] i_LUT_L1;
wire o_Data_L1;

//LUT2	
reg [3:0] i_addr_load_data_L2;
reg i_Data_L2;
wire [3:0] i_LUT_L2;
wire o_Data_L2;

//LUT3
reg [3:0] i_addr_load_data_L3;
reg i_Data_L3;
wire [3:0] i_LUT_L3;
wire o_Data_L3;

//LUT4
reg [3:0] i_addr_load_data_L4;
reg i_Data_L4;
wire [3:0] i_LUT_L4;
wire o_Data_L4;

//LUT5
reg [3:0] i_addr_load_data_L5;
reg i_Data_L5;
wire [3:0] i_LUT_L5;
wire o_Data_L5;

//LUT6
reg [3:0] i_addr_load_data_L6;
reg i_Data_L6;
wire [3:0] i_LUT_L6;
wire o_Data_L6;

//LUT7
reg [3:0] i_addr_load_data_L7;
reg i_Data_L7;
wire [3:0] i_LUT_L7;
wire o_Data_L7;

//LUT8
reg [3:0] i_addr_load_data_L8;
reg i_Data_L8;
wire [3:0] i_LUT_L8;
wire o_Data_L8;

wire i_Data_Mux1;
wire i_Data_Mux2;
wire i_config_enable_L;


assign i_config_enable_L = uio_in[0];
assign uio_oe[0] = 1'b0;
assign uio_out[0] = 1'b1;

assign i_Data_Mux1 = uio_in[1];
assign uio_oe[1] = 1'b0;
assign uio_out[1] = 1'b1;

assign i_Data_Mux2 = uio_in[2];
assign uio_oe[2] = 1'b0;
assign uio_out[2] = 1'b1;

assign Lut_mux = uio_in[4:3];
assign uio_oe[4:3] = 2'b00;
assign uio_out[4:3] = 2'b11;

assign Data_mux = uio_in[5];
assign uio_oe[5] = 1'b0;
assign uio_out[5] = 1'b1;

//To avoid errors
assign uio_oe[7:6] = 2'b00;
assign uio_out[7:6] = 2'b11;

/// Top module conexion
/*
	uio_in[0] --> i_config_enable_L  // 1 write data, 0 read data
	uio_oe[0] <-- 0
	uio_out[0] = 1 //To avoid errors
	
	uio_in[1] --> i_Data_Mux1
	uio_oe[1] <-- 0
	uio_out[1] = 1 //To avoid errors
	
	uio_in[2] --> i_Data_Mux2
	uio_oe[2] <-- 0
	uio_out[2] = 1 //To avoid errors
	
	uio_in[4:3] --> Lut_mux
	uio_oe[4:3] <-- 2'd0
	uio_out[4:3] = 2d'3 //To avoid errors
	
	uio_oe[7:6] <-- 3b'111
	uio_out[7:6] = 3b'111 //To avoid errors
	
		LUT 1
	//Lut_mux = 0 & Data_mux = 0 
	ui_in[3:0] --> i_addr_load_data_L1
	ui_in[7:4] --> i_LUT_L1
	uo_out[0] <-- o_Data_L1
	i_Data_L1 <-- i_Data_Mux1
		LUT 2
	//Lut_mux = 0 & Data_mux = 1 
	ui_in[3:0] --> i_addr_load_data_L2
	ui_in[7:4] --> i_LUT_L2
	uo_out[1] <-- o_Data_L2
	i_Data_L2 <-- i_Data_Mux2
	
		LUT 3
	//Lut_mux = 1 & Data_mux = 0
	ui_in[3:0] --> i_addr_load_data_L3
	ui_in[7:4] --> i_LUT_L3
	uo_out[2] <-- o_Data_L3
	i_Data_L3 <-- i_Data_Mux1
	
		LUT 4
	//Lut_mux = 1 & Data_mux = 1 
	ui_in[3:0] --> i_addr_load_data_L4
	ui_in[7:4] --> i_LUT_L4
	uo_out[3] <-- o_Data_L4
	i_Data_L4 <-- i_Data_Mux2
	
		LUT 5
	//Lut_mux = 10 & Data_mux = 0
	ui_in[3:0] --> i_addr_load_data_L5
	ui_in[7:4] --> i_LUT_L5
	uo_out[4] <-- o_Data_L5
	i_Data_L5 <-- i_Data_Mux1
	
		LUT 6
	//Lut_mux = 10 & Data_mux = 1 
	ui_in[3:0] --> i_addr_load_data_L6
	ui_in[7:4] --> i_LUT_L6
	uo_out[5] <-- o_Data_L6
	i_Data_L6 <-- i_Data_Mux2
	
		LUT 7
	//Lut_mux = 11 & Data_mux = 0
	ui_in[3:0] --> i_addr_load_data_L7
	ui_in[7:4] --> i_LUT_L7
	uo_out[6] <-- o_Data_L7
	i_Data_L7 <-- i_Data_Mux1
	
		LUT 8
	//Lut_mux = 11 & Data_mux = 1 
	ui_in[3:0] --> i_addr_load_data_L8
	ui_in[7:4] --> i_LUT_L8
	uo_out[7] <-- o_Data_L8
	i_Data_L8 <-- i_Data_Mux2
		

*/

assign uo_out = {o_Data_L8,o_Data_L7,o_Data_L6,o_Data_L5,o_Data_L4,o_Data_L3,o_Data_L2,o_Data_L1};
assign i_LUT_L1 = ui_in[7:4]; //Data Lut
assign i_LUT_L2 = ui_in[7:4]; //Data Lut
assign i_LUT_L3 = ui_in[7:4]; //Data Lut
assign i_LUT_L4 = ui_in[7:4]; //Data Lut
assign i_LUT_L5 = ui_in[7:4]; //Data Lut
assign i_LUT_L6 = ui_in[7:4]; //Data Lut
assign i_LUT_L7 = ui_in[7:4]; //Data Lut
assign i_LUT_L8 = ui_in[7:4]; //Data Lut
//Mux Lut_mux

always@*
begin
	case({Lut_mux,Data_mux})
	3'b000:
	begin
		i_addr_load_data_L1= ui_in[3:0]; //Addr Lut
		//i_LUT_L1 = ui_in[7:4]; //Data Lut
		i_Data_L1 = i_Data_Mux1;
	end
	3'b001:
	begin
		i_addr_load_data_L2= ui_in[3:0]; //Addr Lut
		//i_LUT_L2 = ui_in[7:4]; //Data Lut
		i_Data_L2 = i_Data_Mux2;
	end
	3'b010:
	begin
		i_addr_load_data_L3= ui_in[3:0]; //Addr Lut
		//i_LUT_L3 = ui_in[7:4]; //Data Lut
		i_Data_L3 = i_Data_Mux1;
	end
	3'b011:
	begin
		i_addr_load_data_L4= ui_in[3:0]; //Addr Lut
		//i_LUT_L4 = ui_in[7:4]; //Data Lut
		i_Data_L4 = i_Data_Mux2;
	end
	3'b100:
	begin
		i_addr_load_data_L5= ui_in[3:0]; //Addr Lut
		//i_LUT_L5 = ui_in[7:4]; //Data Lut
		i_Data_L5 = i_Data_Mux1;
	end
	3'b101:
	begin
		i_addr_load_data_L6= ui_in[3:0]; //Addr Lut
		//i_LUT_L6 = ui_in[7:4]; //Data Lut
		i_Data_L6 = i_Data_Mux2;
	end
	3'b110:
	begin
		i_addr_load_data_L7= ui_in[3:0]; //Addr Lut
		//i_LUT_L7 = ui_in[7:4]; //Data Lut
		i_Data_L7 = i_Data_Mux1;
	end
	3'b111:
	begin
		i_addr_load_data_L8= ui_in[3:0]; //Addr Lut
		//i_LUT_L8 = ui_in[7:4]; //Data Lut
		i_Data_L8 = i_Data_Mux2;
	end
	endcase
end

	

Single_4LUT LUT_1(
.i_addr_load_data (i_addr_load_data_L1),
.i_Data (i_Data_L1),
.i_LUT (i_LUT_L1),
.i_config_enable (i_config_enable_L),
.o_Data (o_Data_L1)
);

Single_4LUT LUT_2(
.i_addr_load_data (i_addr_load_data_L2),
.i_Data (i_Data_L2),
.i_LUT (i_LUT_L2),
.i_config_enable (i_config_enable_L),
.o_Data (o_Data_L2)
);

Single_4LUT LUT_3(
.i_addr_load_data (i_addr_load_data_L3),
.i_Data (i_Data_L3),
.i_LUT (i_LUT_L3),
.i_config_enable (i_config_enable_L),
.o_Data (o_Data_L3)
);

Single_4LUT LUT_4(
.i_addr_load_data (i_addr_load_data_L4),
.i_Data (i_Data_L4),
.i_LUT (i_LUT_L4),
.i_config_enable (i_config_enable_L),
.o_Data (o_Data_L4)
);

Single_4LUT LUT_5(
.i_addr_load_data (i_addr_load_data_L5),
.i_Data (i_Data_L5),
.i_LUT (i_LUT_L5),
.i_config_enable (i_config_enable_L),
.o_Data (o_Data_L5)
);

Single_4LUT LUT_6(
.i_addr_load_data (i_addr_load_data_L6),
.i_Data (i_Data_L6),
.i_LUT (i_LUT_L6),
.i_config_enable (i_config_enable_L),
.o_Data (o_Data_L6)
);

Single_4LUT LUT_7(
.i_addr_load_data (i_addr_load_data_L7),
.i_Data (i_Data_L7),
.i_LUT (i_LUT_L7),
.i_config_enable (i_config_enable_L),
.o_Data (o_Data_L7)
);

Single_4LUT LUT_8(
.i_addr_load_data (i_addr_load_data_L8),
.i_Data (i_Data_L8),
.i_LUT (i_LUT_L8),
.i_config_enable (i_config_enable_L),
.o_Data (o_Data_L8)
);




endmodule

src/TB_4_LUT_Baungarten.v
module TB_4_LUT_Baungarten();

reg [7:0] ui_in;    // Dedicated inputs - connected to the input switches
wire [7:0] uo_out;   // Dedicated outputs - connected to the 7 segment display
reg [7:0] uio_in;  // IOs: Bidirectional Input path
wire [7:0] uio_out;  // IOs: Bidirectional Output path
wire [7:0] uio_oe;   // IOs: Bidirectional Enable path (active high: 0=input, 1=output)
reg       ena;      // will go high when the design is enabled
reg       clk;      // clock
reg       rst_n;     // reset_n - low to reset

tt_um_4_LUT_Baungarten DUT(
    .ui_in(ui_in),    // Dedicated inputs - connected to the input switches
    .uo_out(uo_out),   // Dedicated outputs - connected to the 7 segment display
    .uio_in(uio_in),   // IOs: Bidirectional Input path
    .uio_out(uio_out),  // IOs: Bidirectional Output path
    .uio_oe(uio_oe),   // IOs: Bidirectional Enable path (active high: 0=input, 1=output)
    .ena(ena),      // will go high when the design is enabled
    .clk(clk),      // clock
    .rst_n(rst_n)     // reset_n - low to reset
);




initial
begin
rst_n = 0;
clk = 0; 
ena = 1;
ui_in[3:0] = 0; //addrs
ui_in[7:4] = 0; //data
uio_in[0] = 1;//enable write
uio_in[1] = 0;//data_mux1
uio_in[2] = 0;//data_mux2
uio_in[4:3] = 0;//Lut_mux 1&2, 3&4,5&6, 7&8
uio_in[5]=0;
#50;
//a segment
uio_in[4:3] = 0;
uio_in[5]=0;
uio_in[1] = 1;//data_mux1
ui_in[3:0] = 0;
#50;
uio_in[1] = 0;//data_mux1
ui_in[3:0] = 1;
#50;
uio_in[1] = 1;//data_mux1
ui_in[3:0] = 2;
#50;
uio_in[1] = 1;//data_mux1
ui_in[3:0] = 3;

#50;
uio_in[1] = 0;//data_mux1
ui_in[3:0] = 4;
#50;
uio_in[1] = 1;//data_mux1
ui_in[3:0] = 5;
#50;
uio_in[1] = 0;//data_mux1
ui_in[3:0] = 6;
#50;
uio_in[1] = 1;//data_mux1
ui_in[3:0] = 7;

#50;
uio_in[1] = 1;//data_mux1
ui_in[3:0] = 8;
#50;
uio_in[1] = 1;//data_mux1
ui_in[3:0] = 9;
#50;
uio_in[1] = 0;//data_mux1
ui_in[3:0] = 10;
#50;
uio_in[1] = 0;//data_mux1
ui_in[3:0] = 11;

#50;
uio_in[1] = 0;//data_mux1
ui_in[3:0] = 12;
#50;
uio_in[1] = 1;//data_mux1
ui_in[3:0] = 13;
#50;
uio_in[1] = 0;//data_mux1
ui_in[3:0] = 14;
#50;
uio_in[1] = 0;//data_mux1
ui_in[3:0] = 15;



//////////////////b segment///////////////////
uio_in[5]=1;
uio_in[2] = 1;//data_mux1
ui_in[3:0] = 0;
#50;
uio_in[2] = 1;//data_mux1
ui_in[3:0] = 1;
#50;
uio_in[2] = 1;//data_mux1
ui_in[3:0] = 2;
#50;
uio_in[2] = 1;//data_mux1
ui_in[3:0] = 3;

#50;
uio_in[2] = 1;//data_mux1
ui_in[3:0] = 4;
#50;
uio_in[2] = 0;//data_mux1
ui_in[3:0] = 5;
#50;
uio_in[2] = 0;//data_mux1
ui_in[3:0] = 6;
#50;
uio_in[2] = 1;//data_mux1
ui_in[3:0] = 7;

#50;
uio_in[2] = 1;//data_mux1
ui_in[3:0] = 8;
#50;
uio_in[2] = 1;//data_mux1
ui_in[3:0] = 9;
#50;
uio_in[2] = 0;//data_mux1
ui_in[3:0] = 10;
#50;
uio_in[2] = 0;//data_mux1
ui_in[3:0] = 11;

#50;
uio_in[2] = 1;//data_mux1
ui_in[3:0] = 12;
#50;
uio_in[2] = 0;//data_mux1
ui_in[3:0] = 13;
#50;
uio_in[2] = 0;//data_mux1
ui_in[3:0] = 14;
#50;
uio_in[2] = 0;//data_mux1
ui_in[3:0] = 15;

//////////////////c segment///////////////////
uio_in[5]=0;
uio_in[4:3] = 1;
uio_in[1] = 1;//data_mux1
ui_in[3:0] = 0;
#50;
uio_in[1] = 1;//data_mux1
ui_in[3:0] = 1;
#50;
uio_in[1] = 0;//data_mux1
ui_in[3:0] = 2;
#50;
uio_in[1] = 1;//data_mux1
ui_in[3:0] = 3;

#50;
uio_in[1] = 1;//data_mux1
ui_in[3:0] = 4;
#50;
uio_in[1] = 1;//data_mux1
ui_in[3:0] = 5;
#50;
uio_in[1] = 1;//data_mux1
ui_in[3:0] = 6;
#50;
uio_in[1] = 1;//data_mux1
ui_in[3:0] = 7;

#50;
uio_in[1] = 1;//data_mux1
ui_in[3:0] = 8;
#50;
uio_in[1] = 1;//data_mux1
ui_in[3:0] = 9;
#50;
uio_in[1] = 0;//data_mux1
ui_in[3:0] = 10;
#50;
uio_in[1] = 1;//data_mux1
ui_in[3:0] = 11;

#50;
uio_in[1] = 0;//data_mux1
ui_in[3:0] = 12;
#50;
uio_in[1] = 0;//data_mux1
ui_in[3:0] = 13;
#50;
uio_in[1] = 0;//data_mux1
ui_in[3:0] = 14;
#50;
uio_in[1] = 0;//data_mux1
ui_in[3:0] = 15;

//////////////////d segment///////////////////
uio_in[5]=1;
uio_in[2] = 1;//data_mux1
ui_in[3:0] = 0;
#50;
uio_in[2] = 0;//data_mux1
ui_in[3:0] = 1;
#50;
uio_in[2] = 1;//data_mux1
ui_in[3:0] = 2;
#50;
uio_in[2] = 1;//data_mux1
ui_in[3:0] = 3;

#50;
uio_in[2] = 0;//data_mux1
ui_in[3:0] = 4;
#50;
uio_in[2] = 1;//data_mux1
ui_in[3:0] = 5;
#50;
uio_in[2] = 1;//data_mux1
ui_in[3:0] = 6;
#50;
uio_in[2] = 0;//data_mux1
ui_in[3:0] = 7;

#50;
uio_in[2] = 1;//data_mux1
ui_in[3:0] = 8;
#50;
uio_in[2] = 0;//data_mux1
ui_in[3:0] = 9;
#50;
uio_in[2] = 1;//data_mux1
ui_in[3:0] = 10;
#50;
uio_in[2] = 1;//data_mux1
ui_in[3:0] = 11;

#50;
uio_in[2] = 0;//data_mux1
ui_in[3:0] = 12;
#50;
uio_in[2] = 1;//data_mux1
ui_in[3:0] = 13;
#50;
uio_in[2] = 1;//data_mux1
ui_in[3:0] = 14;
#50;
uio_in[2] = 0;//data_mux1
ui_in[3:0] = 15;

/////////////////e segment///////////////////
uio_in[5]=0;
uio_in[4:3] = 2;
uio_in[1] = 1;//data_mux1
ui_in[3:0] = 0;
#50;
uio_in[1] = 0;//data_mux1
ui_in[3:0] = 1;
#50;
uio_in[1] = 1;//data_mux1
ui_in[3:0] = 2;
#50;
uio_in[1] = 0;//data_mux1
ui_in[3:0] = 3;

#50;
uio_in[1] = 0;//data_mux1
ui_in[3:0] = 4;
#50;
uio_in[1] = 0;//data_mux1
ui_in[3:0] = 5;
#50;
uio_in[1] = 1;//data_mux1
ui_in[3:0] = 6;
#50;
uio_in[1] = 0;//data_mux1
ui_in[3:0] = 7;

#50;
uio_in[1] = 1;//data_mux1
ui_in[3:0] = 8;
#50;
uio_in[1] = 0;//data_mux1
ui_in[3:0] = 9;
#50;
uio_in[1] = 1;//data_mux1
ui_in[3:0] = 10;
#50;
uio_in[1] = 0;//data_mux1
ui_in[3:0] = 11;

#50;
uio_in[1] = 0;//data_mux1
ui_in[3:0] = 12;
#50;
uio_in[1] = 0;//data_mux1
ui_in[3:0] = 13;
#50;
uio_in[1] = 1;//data_mux1
ui_in[3:0] = 14;
#50;
uio_in[1] = 0;//data_mux1
ui_in[3:0] = 15;

//////////////////d segment///////////////////
uio_in[5]=1;
uio_in[2] = 1;//data_mux1
ui_in[3:0] = 0;
#50;
uio_in[2] = 0;//data_mux1
ui_in[3:0] = 1;
#50;
uio_in[2] = 0;//data_mux1
ui_in[3:0] = 2;
#50;
uio_in[2] = 0;//data_mux1
ui_in[3:0] = 3;

#50;
uio_in[2] = 1;//data_mux1
ui_in[3:0] = 4;
#50;
uio_in[2] = 1;//data_mux1
ui_in[3:0] = 5;
#50;
uio_in[2] = 1;//data_mux1
ui_in[3:0] = 6;
#50;
uio_in[2] = 0;//data_mux1
ui_in[3:0] = 7;

#50;
uio_in[2] = 1;//data_mux1
ui_in[3:0] = 8;
#50;
uio_in[2] = 1;//data_mux1
ui_in[3:0] = 9;
#50;
uio_in[2] = 0;//data_mux1
ui_in[3:0] = 10;
#50;
uio_in[2] = 0;//data_mux1
ui_in[3:0] = 11;

#50;
uio_in[2] = 1;//data_mux1
ui_in[3:0] = 12;
#50;
uio_in[2] = 1;//data_mux1
ui_in[3:0] = 13;
#50;
uio_in[2] = 1;//data_mux1
ui_in[3:0] = 14;
#50;
uio_in[2] = 0;//data_mux1
ui_in[3:0] = 15;

/////////////////e segment///////////////////
uio_in[5]=0;
uio_in[4:3] = 3;
uio_in[1] = 0;//data_mux1
ui_in[3:0] = 0;
#50;
uio_in[1] = 0;//data_mux1
ui_in[3:0] = 1;
#50;
uio_in[1] = 1;//data_mux1
ui_in[3:0] = 2;
#50;
uio_in[1] = 1;//data_mux1
ui_in[3:0] = 3;

#50;
uio_in[1] = 1;//data_mux1
ui_in[3:0] = 4;
#50;
uio_in[1] = 1;//data_mux1
ui_in[3:0] = 5;
#50;
uio_in[1] = 1;//data_mux1
ui_in[3:0] = 6;
#50;
uio_in[1] = 0;//data_mux1
ui_in[3:0] = 7;

#50;
uio_in[1] = 1;//data_mux1
ui_in[3:0] = 8;
#50;
uio_in[1] = 1;//data_mux1
ui_in[3:0] = 9;
#50;
uio_in[1] = 1;//data_mux1
ui_in[3:0] = 10;
#50;
uio_in[1] = 1;//data_mux1
ui_in[3:0] = 11;

#50;
uio_in[1] = 1;//data_mux1
ui_in[3:0] = 12;
#50;
uio_in[1] = 1;//data_mux1
ui_in[3:0] = 13;
#50;
uio_in[1] = 1;//data_mux1
ui_in[3:0] = 14;
#50;
uio_in[1] = 0;//data_mux1
ui_in[3:0] = 15;
#200;
uio_in[0] = 0;//enable read
ui_in[7:4] = ui_in[7:4] +1;
#50;
ui_in[7:4] = ui_in[7:4] +1;
#50;
ui_in[7:4] = ui_in[7:4] +1;
#50;
ui_in[7:4] = ui_in[7:4] +1;
#50;
ui_in[7:4] = ui_in[7:4] +1;
#50;
ui_in[7:4] = ui_in[7:4] +1;
#50;
ui_in[7:4] = ui_in[7:4] +1;
#50;
ui_in[7:4] = ui_in[7:4] +1;
#50;
ui_in[7:4] = ui_in[7:4] +1;
#50;
ui_in[7:4] = ui_in[7:4] +1;
#50;
ui_in[7:4] = ui_in[7:4] +1;
#50;
ui_in[7:4] = ui_in[7:4] +1;
#50;
ui_in[7:4] = ui_in[7:4] +1;
#50;
ui_in[7:4] = ui_in[7:4] +1;
#50;
ui_in[7:4] = ui_in[7:4] +1;
#50;
ui_in[7:4] = ui_in[7:4] +1;
#50;
ui_in[7:4] = ui_in[7:4] +1;
#50;
ui_in[7:4] = ui_in[7:4] +1;
#50;
ui_in[7:4] = ui_in[7:4] +1;
#50;
ui_in[7:4] = ui_in[7:4] +1;
#50;
ui_in[7:4] = ui_in[7:4] +1;
#50;
ui_in[7:4] = ui_in[7:4] +1;
#50;
ui_in[7:4] = ui_in[7:4] +1;
#50;
ui_in[7:4] = ui_in[7:4] +1;
#50;
end

  initial
  begin
  $dumpfile("TB_4_LUT_Baungarten.vcd");
  $dumpvars;
  end
endmodule

src/TB_4_LUT_Baungarten.vcd
$date
	Mon Aug 28 20:26:31 2023
$end
$version
	Icarus Verilog
$end
$timescale
	1s
$end
$scope module TB_4_LUT_Baungarten $end
$var wire 8 ! uo_out [7:0] $end
$var wire 8 " uio_out [7:0] $end
$var wire 8 # uio_oe [7:0] $end
$var reg 1 $ clk $end
$var reg 1 % ena $end
$var reg 1 & rst_n $end
$var reg 8 ' ui_in [7:0] $end
$var reg 8 ( uio_in [7:0] $end
$scope module DUT $end
$var wire 1 $ clk $end
$var wire 1 % ena $end
$var wire 1 & rst_n $end
$var wire 8 ) ui_in [7:0] $end
$var wire 8 * uio_in [7:0] $end
$var wire 8 + uo_out [7:0] $end
$var wire 8 , uio_out [7:0] $end
$var wire 8 - uio_oe [7:0] $end
$var wire 1 . o_Data_L8 $end
$var wire 1 / o_Data_L7 $end
$var wire 1 0 o_Data_L6 $end
$var wire 1 1 o_Data_L5 $end
$var wire 1 2 o_Data_L4 $end
$var wire 1 3 o_Data_L3 $end
$var wire 1 4 o_Data_L2 $end
$var wire 1 5 o_Data_L1 $end
$var wire 1 6 i_config_enable_L $end
$var wire 4 7 i_LUT_L8 [3:0] $end
$var wire 4 8 i_LUT_L7 [3:0] $end
$var wire 4 9 i_LUT_L6 [3:0] $end
$var wire 4 : i_LUT_L5 [3:0] $end
$var wire 4 ; i_LUT_L4 [3:0] $end
$var wire 4 < i_LUT_L3 [3:0] $end
$var wire 4 = i_LUT_L2 [3:0] $end
$var wire 4 > i_LUT_L1 [3:0] $end
$var wire 1 ? i_Data_Mux2 $end
$var wire 1 @ i_Data_Mux1 $end
$var wire 2 A Lut_mux [1:0] $end
$var wire 1 B Data_mux $end
$var reg 1 C i_Data_L1 $end
$var reg 1 D i_Data_L2 $end
$var reg 1 E i_Data_L3 $end
$var reg 1 F i_Data_L4 $end
$var reg 1 G i_Data_L5 $end
$var reg 1 H i_Data_L6 $end
$var reg 1 I i_Data_L7 $end
$var reg 1 J i_Data_L8 $end
$var reg 4 K i_addr_load_data_L1 [3:0] $end
$var reg 4 L i_addr_load_data_L2 [3:0] $end
$var reg 4 M i_addr_load_data_L3 [3:0] $end
$var reg 4 N i_addr_load_data_L4 [3:0] $end
$var reg 4 O i_addr_load_data_L5 [3:0] $end
$var reg 4 P i_addr_load_data_L6 [3:0] $end
$var reg 4 Q i_addr_load_data_L7 [3:0] $end
$var reg 4 R i_addr_load_data_L8 [3:0] $end
$scope module LUT_1 $end
$var wire 1 C i_Data $end
$var wire 4 S i_LUT [3:0] $end
$var wire 4 T i_addr_load_data [3:0] $end
$var wire 1 6 i_config_enable $end
$var reg 1 5 o_Data $end
$var reg 16 U r_data [15:0] $end
$upscope $end
$scope module LUT_2 $end
$var wire 1 D i_Data $end
$var wire 4 V i_LUT [3:0] $end
$var wire 4 W i_addr_load_data [3:0] $end
$var wire 1 6 i_config_enable $end
$var reg 1 4 o_Data $end
$var reg 16 X r_data [15:0] $end
$upscope $end
$scope module LUT_3 $end
$var wire 1 E i_Data $end
$var wire 4 Y i_LUT [3:0] $end
$var wire 4 Z i_addr_load_data [3:0] $end
$var wire 1 6 i_config_enable $end
$var reg 1 3 o_Data $end
$var reg 16 [ r_data [15:0] $end
$upscope $end
$scope module LUT_4 $end
$var wire 1 F i_Data $end
$var wire 4 \ i_LUT [3:0] $end
$var wire 4 ] i_addr_load_data [3:0] $end
$var wire 1 6 i_config_enable $end
$var reg 1 2 o_Data $end
$var reg 16 ^ r_data [15:0] $end
$upscope $end
$scope module LUT_5 $end
$var wire 1 G i_Data $end
$var wire 4 _ i_LUT [3:0] $end
$var wire 4 ` i_addr_load_data [3:0] $end
$var wire 1 6 i_config_enable $end
$var reg 1 1 o_Data $end
$var reg 16 a r_data [15:0] $end
$upscope $end
$scope module LUT_6 $end
$var wire 1 H i_Data $end
$var wire 4 b i_LUT [3:0] $end
$var wire 4 c i_addr_load_data [3:0] $end
$var wire 1 6 i_config_enable $end
$var reg 1 0 o_Data $end
$var reg 16 d r_data [15:0] $end
$upscope $end
$scope module LUT_7 $end
$var wire 1 I i_Data $end
$var wire 4 e i_LUT [3:0] $end
$var wire 4 f i_addr_load_data [3:0] $end
$var wire 1 6 i_config_enable $end
$var reg 1 / o_Data $end
$var reg 16 g r_data [15:0] $end
$upscope $end
$scope module LUT_8 $end
$var wire 1 J i_Data $end
$var wire 4 h i_LUT [3:0] $end
$var wire 4 i i_addr_load_data [3:0] $end
$var wire 1 6 i_config_enable $end
$var reg 1 . o_Data $end
$var reg 16 j r_data [15:0] $end
$upscope $end
$upscope $end
$upscope $end
$enddefinitions $end
#0
$dumpvars
bx j
bx i
b0 h
bx g
bx f
b0 e
bx d
bx c
b0 b
bx a
bx `
b0 _
bx ^
bx ]
b0 \
bx [
bx Z
b0 Y
bx X
bx W
b0 V
bx0 U
b0 T
b0 S
bx R
bx Q
bx P
bx O
bx N
bx M
bx L
b0 K
xJ
xI
xH
xG
xF
xE
xD
0C
0B
b0 A
0@
0?
b0 >
b0 =
b0 <
b0 ;
b0 :
b0 9
b0 8
b0 7
16
x5
x4
x3
x2
x1
x0
x/
x.
b0 -
b11111111 ,
bx +
bx000001 *
b0 )
bx000001 (
b0 '
0&
1%
0$
b0 #
b11111111 "
bx !
$end
#50
bx1 U
1C
1@
bx000011 (
bx000011 *
#100
bx01 U
0C
b1 K
b1 T
0@
b1 '
b1 )
bx000001 (
bx000001 *
#150
bx101 U
1C
b10 K
b10 T
1@
b10 '
b10 )
bx000011 (
bx000011 *
#200
bx1101 U
b11 K
b11 T
b11 '
b11 )
#250
bx01101 U
0C
b100 K
b100 T
0@
b100 '
b100 )
bx000001 (
bx000001 *
#300
bx101101 U
1C
b101 K
b101 T
1@
b101 '
b101 )
bx000011 (
bx000011 *
#350
bx0101101 U
0C
b110 K
b110 T
0@
b110 '
b110 )
bx000001 (
bx000001 *
#400
bx10101101 U
1C
b111 K
b111 T
1@
b111 '
b111 )
bx000011 (
bx000011 *
#450
bx110101101 U
b1000 K
b1000 T
b1000 '
b1000 )
#500
bx1110101101 U
b1001 K
b1001 T
b1001 '
b1001 )
#550
bx01110101101 U
0C
b1010 K
b1010 T
0@
b1010 '
b1010 )
bx000001 (
bx000001 *
#600
bx001110101101 U
b1011 K
b1011 T
b1011 '
b1011 )
#650
bx0001110101101 U
b1100 K
b1100 T
b1100 '
b1100 )
#700
bx10001110101101 U
1C
b1101 K
b1101 T
1@
b1101 '
b1101 )
bx000011 (
bx000011 *
#750
bx010001110101101 U
0C
b1110 K
b1110 T
0@
b1110 '
b1110 )
bx000001 (
bx000001 *
#800
bx1 X
1D
b0 L
b0 W
bx010001110101100 U
1?
1B
b0 K
b0 T
bx100101 (
bx100101 *
b0 '
b0 )
#850
bx11 X
b1 L
b1 W
b1 '
b1 )
#900
bx111 X
b10 L
b10 W
b10 '
b10 )
#950
bx1111 X
b11 L
b11 W
b11 '
b11 )
#1000
bx11111 X
b100 L
b100 W
b100 '
b100 )
#1050
bx011111 X
0D
b101 L
b101 W
0?
b101 '
b101 )
bx100001 (
bx100001 *
#1100
bx0011111 X
b110 L
b110 W
b110 '
b110 )
#1150
bx10011111 X
1D
b111 L
b111 W
1?
b111 '
b111 )
bx100101 (
bx100101 *
#1200
bx110011111 X
b1000 L
b1000 W
b1000 '
b1000 )
#1250
bx1110011111 X
b1001 L
b1001 W
b1001 '
b1001 )
#1300
bx01110011111 X
0D
b1010 L
b1010 W
0?
b1010 '
b1010 )
bx100001 (
bx100001 *
#1350
bx001110011111 X
b1011 L
b1011 W
b1011 '
b1011 )
#1400
bx1001110011111 X
1D
b1100 L
b1100 W
1?
b1100 '
b1100 )
bx100101 (
bx100101 *
#1450
bx01001110011111 X
0D
b1101 L
b1101 W
0?
b1101 '
b1101 )
bx100001 (
bx100001 *
#1500
bx001001110011111 X
b1110 L
b1110 W
b1110 '
b1110 )
#1550
bx1 [
1E
b0 M
b0 Z
bx001001110011110 X
1@
b1 A
0B
b0 L
b0 W
bx001011 (
bx001011 *
b0 '
b0 )
#1600
bx11 [
b1 M
b1 Z
b1 '
b1 )
#1650
bx011 [
0E
b10 M
b10 Z
0@
b10 '
b10 )
bx001001 (
bx001001 *
#1700
bx1011 [
1E
b11 M
b11 Z
1@
b11 '
b11 )
bx001011 (
bx001011 *
#1750
bx11011 [
b100 M
b100 Z
b100 '
b100 )
